src/LFSRmod.v
`default_nettype none
`timescale 1ns/1ps
module LFSRmod (CLOCK, RESET, ENABLE, OUTDATA);
	input wire CLOCK, RESET, ENABLE;
	output reg [4:0] OUTDATA;

	reg value;
	reg [18:0] out;

	always @(*) begin
		value = ~(out[18] ^ out[5] ^ out[1] ^ out[0]);
		OUTDATA = out[18:14];
	end

	always @(posedge CLOCK) begin
		if (RESET) begin
			out <= 19'h1;
		end

		else begin
			if(ENABLE)
			begin
				out[18:0] <= { value , out[18:1] };
			end
		end
	end
endmodule

LFSRmod.vcd
$date
	Wed Aug 31 23:13:50 2022
$end
$version
	Icarus Verilog
$end
$timescale
	1ps
$end
$scope module LFSRmod $end
$var wire 1 ! CLOCK $end
$var wire 1 " ENABLE $end
$var wire 1 # RESET $end
$var reg 5 $ OUTDATA [4:0] $end
$var reg 19 % out [18:0] $end
$var reg 1 & value $end
$upscope $end
$enddefinitions $end
#0
$dumpvars
0&
b1 %
b0 $
1#
0"
1!
$end
#5000
0!
#10000
1!
#15000
0!
#20000
1!
#25000
0!
#30000
1!
#35000
0!
#40000
1!
#45000
0!
#50000
1!
#55000
0!
#60000
1!
#65000
0!
#70000
1!
#75000
0!
#80000
1!
#85000
0!
#90000
1!
#95000
0!
#100000
1!
#105000
0!
#110000
1!
#115000
0!
#120000
1!
#125000
0!
#130000
1!
#135000
0!
#140000
1!
#145000
0!
#150000
1!
#155000
0!
#160000
1!
#165000
0!
#170000
1!
#175000
0!
#180000
1!
#185000
0!
#190000
1!
#195000
0!
#200000
1!
#205000
0!
#210000
1!
#215000
0!
#220000
1!
#225000
0!
#230000
1!
#235000
0!
#240000
1!
#245000
0!
#250000
1!
#255000
0!
#260000
1!
#265000
0!
#270000
1!
#275000
0!
#280000
1!
#285000
0!
#290000
1!
#295000
0!
#300000
1!
#305000
0!
#310000
1!
#315000
0!
#320000
1!
#325000
0!
#330000
1!
#335000
0!
#340000
1!
#345000
0!
#350000
1!
#355000
0!
#360000
1!
#365000
0!
#370000
1!
#375000
0!
#380000
1!
#385000
0!
#390000
1!
#395000
0!
#400000
1!
#405000
0!
#410000
1!
#415000
0!
#420000
1!
#425000
0!
#430000
1!
#435000
0!
#440000
1!
#445000
0!
#450000
1!
#455000
0!
#460000
1!
#465000
0!
#470000
1!
#475000
0!
#480000
1!
#485000
0!
#490000
0#
1!
#495000
0!
#500000
1!
#505000
0!
#510000
1!
#515000
0!
#520000
1!
#525000
0!
#530000
1!
#535000
0!
#540000
1!
#545000
0!
#550000
1!
#555000
0!
#560000
1!
#565000
0!
#570000
1!
#575000
0!
#580000
1!
#585000
0!
#590000
1!
#595000
0!
#600000
1!
#605000
0!
#610000
1!
#615000
0!
#620000
1!
#625000
0!
#630000
1!
#635000
0!
#640000
1!
#645000
0!
#650000
1!
#655000
0!
#660000
1!
#665000
0!
#670000
1!
#675000
0!
#680000
1!
#685000
0!
#690000
1!
#695000
0!
#700000
1!
#705000
0!
#710000
1!
#715000
0!
#720000
1!
#725000
0!
#730000
1!
#735000
0!
#740000
1!
#745000
0!
#750000
1!
#755000
0!
#760000
1!
#765000
0!
#770000
1!
#775000
0!
#780000
1!
#785000
0!
#790000
1!
#795000
0!
#800000
1!
#805000
0!
#810000
1!
#815000
0!
#820000
1!
#825000
0!
#830000
1!
#835000
0!
#840000
1!
#845000
0!
#850000
1!
#855000
0!
#860000
1!
#865000
0!
#870000
1!
#875000
0!
#880000
1!
#885000
0!
#890000
1!
#895000
0!
#900000
1!
#905000
0!
#910000
1!
#915000
0!
#920000
1!
#925000
0!
#930000
1!
#935000
0!
#940000
1!
#945000
0!
#950000
1!
#955000
0!
#960000
1!
#965000
0!
#970000
1!
#975000
0!
#980000
1!
#985000
0!
#990000
1!
#995000
0!
#1000000
1!
#1005000
0!
#1010000
1!
#1015000
0!
#1020000
1!
#1025000
0!
#1030000
1!
#1035000
0!
#1040000
1!
#1045000
0!
#1050000
1!
#1055000
0!
#1060000
1!
#1065000
0!
#1070000
1!
#1075000
0!
#1080000
1!
#1085000
0!
#1090000
1"
1!
#1095000
0!
#1100000
1&
b0 %
1!
#1105000
0!
#1110000
b10000 $
0&
b1000000000000000000 %
1!
#1115000
0!
#1120000
b1000 $
1&
b100000000000000000 %
1!
#1125000
0!
#1130000
b10100 $
0&
b1010000000000000000 %
1!
#1135000
0!
#1140000
b1010 $
1&
b101000000000000000 %
1!
#1145000
0!
#1150000
b10101 $
0&
b1010100000000000000 %
1!
#1155000
0!
#1160000
b1010 $
1&
b101010000000000000 %
1!
#1165000
0!
#1170000
b10101 $
0&
b1010101000000000000 %
1!
#1175000
0!
#1180000
b1010 $
1&
b101010100000000000 %
1!
#1185000
0!
#1190000
b10101 $
0&
b1010101010000000000 %
1!
#1195000
0!
#1200000
b1010 $
1&
b101010101000000000 %
1!
#1205000
0!
#1210000
b10101 $
0&
b1010101010100000000 %
1!
#1215000
0!
#1220000
b1010 $
1&
b101010101010000000 %
1!
#1225000
0!
#1230000
b10101 $
0&
b1010101010101000000 %
1!
#1235000
0!
#1240000
b1010 $
b101010101010100000 %
1!
#1245000
0!
#1250000
b101 $
1&
b10101010101010000 %
1!
#1255000
0!
#1260000
b10010 $
b1001010101010101000 %
1!
#1265000
0!
#1270000
b11001 $
0&
b1100101010101010100 %
1!
#1275000
0!
#1280000
b1100 $
1&
b110010101010101010 %
1!
#1285000
0!
#1290000
b10110 $
b1011001010101010101 %
1!
#1295000
0!
#1300000
b11011 $
0&
b1101100101010101010 %
1!
