src/LFSRmod.v
`default_nettype none
`timescale 1ns/1ps
module LFSRmod (CLOCK, RESET, ENABLE, OUTDATA);
	input wire CLOCK, RESET, ENABLE;
	output reg [4:0] OUTDATA;

	reg value;
	reg [18:0] out;

	always @(*) begin
		value = ~(out[18] ^ out[5] ^ out[1] ^ out[0]);
		OUTDATA = out[18:14];
	end

	always @(posedge CLOCK) begin
		if (RESET) begin
			out <= 19'h1;
		end

		else begin
			if(ENABLE)
			begin
				out[18:0] <= { value , out[18:1] };
			end
		end
	end
endmodule

src/SymbLUT.v
`default_nettype none
`timescale 1ns/1ps
module SymbLUT(CLOCK, RESET, READY, SHIFT, ADDRESS, DOUTREAL, DOUTIMAG);
	input wire CLOCK;
	input wire RESET;
	input wire READY;
	input wire SHIFT;
	input wire [4:0] ADDRESS;
	output reg DOUTREAL;
	output reg DOUTIMAG;

	wire [127:0] dataREAL [31:0];
	wire [127:0] dataIMAG [31:0];
	reg [4:0]	 dataADDR_d,dataADDR_q;
	reg [127:0] databuffREAL,databuffIMAG;

	always @(*)
	 	begin
			DOUTREAL = databuffREAL[127];
			DOUTIMAG = databuffIMAG[127];
		end

	always @(posedge CLOCK)
		begin
			if(RESET)
			begin
				dataADDR_d <= 0;
				databuffREAL <= 0;
				databuffIMAG <= 0;
			end
			else
			begin

			/////////// UPDATE LUT ADDRESS  ////////////

				if(READY)
				begin
					dataADDR_d <= ADDRESS;
					databuffREAL <= dataREAL[dataADDR_q];
					databuffIMAG <= dataIMAG[dataADDR_q];
				end
				else
				begin
					dataADDR_d <= dataADDR_d;

					if(SHIFT)
					begin
						databuffREAL <= {databuffREAL[126:0],1'b0};
						databuffIMAG <= {databuffIMAG[126:0],1'b0};
					end
				end

			/////////// 	SHIFT DATA		 ////////////

			end
		end

	always @(posedge CLOCK)
		begin
			if(RESET)
			begin
				dataADDR_q <= 0;
			end
			else
			begin
				dataADDR_q <= dataADDR_d;
			end
		end

	assign dataREAL[0] = 128'b00110000000011001100001110000011100110111111111001111100111111011101111110011111001111111110110011100000111000011001100000000110;
	assign dataREAL[1] = 128'b00011000000110011000001101100011110011001101110011111001001110111110111001001111100111011001100111100011011000001100110000001100;
	assign dataIMAG[0] = 128'b11100100111110011001111100111111001111111111110111100001111100111001100000111100001000000000000110000001100000110011000001101100;
	assign dataIMAG[1] = 128'b11110011011100111100111011001111101110111011100111100011111000111001110000011100001100010001000110000110010001100001100010011000;
	assign dataREAL[2] = 128'b00001100011001001000000110000011101000110011000011111100111111111111111110011111100001100110001011100000110000001001001100011000;
	assign dataREAL[3] = 128'b00011100000100110010001111000110110001101111100111111000111101110111011110001111110011111011000110110001111000100110010000011100;
	assign dataREAL[4] = 128'b00100011000011001000110000110001101100011110011011100111001111001001111001110011101100111100011011000110000110001001100001100010;
	assign dataREAL[5] = 128'b00000001000011110000011001100000111010011100100111111011001111110111111001101111110010011100101110000011001100000111100001000000;
	assign dataREAL[6] = 128'b00000110000001100000100110011000111100111111001111101110111111100011111110111011111001111110011110001100110010000011000000110000;
	assign dataREAL[7] = 128'b10001100000000110001001100000100111000011111000110011111011111100011111101111100110001111100001110010000011001000110000000011000;
	assign dataREAL[8] = 128'b00100000011000001100000000010011000111110001111001100111111110011100111111110011001111000111110001100100000000011000001100000010;
	assign dataREAL[9] = 128'b00010001101100001110001001100110000111001001111110110011111100111110011111100110111111001001110000110011001000111000011011000100;
	assign dataREAL[10] = 128'b00000000011000001111100110011101000111110011111111101100111001111111001110011011111111100111110001011100110011111000001100000000;
	assign dataREAL[11] = 128'b10001000011100000011000001001110010011100001110110011011111000111110001111101100110111000011100100111001000001100000011100001000;
	assign dataREAL[12] = 128'b01100001100011001100110000111001001110011110011111100111100111011101110011110011111100111100111001001110000110011001100011000011;
	assign dataREAL[13] = 128'b10000001100100000011011000110100011111001100111110000111101111111111111011110000111110011001111100010110001101100000010011000000;
	assign dataREAL[14] = 128'b11000000010001000001100000011000011100110011011111001111110011111111100111111001111101100110011100001100000011000001000100000001;
	assign dataREAL[15] = 128'b11000000100000110011100000111100011011111001101110011111111001110111001111111100111011001111101100011110000011100110000010000001;
	assign dataREAL[16] = 128'b00111111011111001100011111000011100100000110010001100000000110001000110000000011000100110000010011100001111100011001111101111110;
	assign dataREAL[17] = 128'b00111111101110111110011111100111100011001100100000110000001100000000011000000110000010011001100011110011111100111110111011111110;
	assign dataREAL[18] = 128'b01111110011011111100100111001011100000110011000001111000010000000000000100001111000001100110000011101001110010011111101100111111;
	assign dataREAL[19] = 128'b10011110011100111011001111000110110001100001100010011000011000100010001100001100100011000011000110110001111001101110011100111100;
	assign dataREAL[20] = 128'b01110111100011111100111110110001101100011110001001100100000111000001110000010011001000111100011011000110111110011111100011110111;
	assign dataREAL[21] = 128'b11111111100111111000011001100010111000001100000010010011000110000000110001100100100000011000001110100011001100001111110011111111;
	assign dataREAL[22] = 128'b11101110010011111001110110011001111000110110000011001100000011000001100000011001100000110110001111001100110111001111100100111011;
	assign dataREAL[23] = 128'b11011111100111110011111111101100111000001110000110011000000001100011000000001100110000111000001110011011111111100111110011111101;
	assign dataREAL[24] = 128'b01110011111111001110110011111011000111100000111001100000100000011100000010000011001110000011110001101111100110111001111111100111;
	assign dataREAL[25] = 128'b11111001111110011111011001100111000011000000110000010001000000011100000001000100000110000001100001110011001101111100111111001111;
	assign dataREAL[26] = 128'b11111110111100001111100110011111000101100011011000000100110000001000000110010000001101100011010001111100110011111000011110111111;
	assign dataREAL[27] = 128'b11011100111100111111001111001110010011100001100110011000110000110110000110001100110011000011100100111001111001111110011110011101;
	assign dataREAL[28] = 128'b11100011111011001101110000111001001110010000011000000111000010001000100001110000001100000100111001001110000111011001101111100011;
	assign dataREAL[29] = 128'b11110011100110111111111001111100010111001100111110000011000000000000000001100000111110011001110100011111001111111110110011100111;
	assign dataREAL[30] = 128'b11100111111001101111110010011100001100110010001110000110110001000001000110110000111000100110011000011100100111111011001111110011;
	assign dataREAL[31] = 128'b11001111111100110011110001111100011001000000000110000011000000100010000001100000110000000001001100011111000111100110011111111001;
	assign dataIMAG[0] = 128'b11100100111110011001111100111111001111111111110111100001111100111001100000111100001000000000000110000001100000110011000001101100;
	assign dataIMAG[1] = 128'b11110011011100111100111011001111101110111011100111100011111000111001110000011100001100010001000110000110010001100001100010011000;
	assign dataIMAG[2] = 128'b11111000110011111011111100011111111011101110011111110001110010011011011000111000000011000100010010000011100000010000011001110000;
	assign dataIMAG[3] = 128'b10111000111001100110111100011111100111111111001111110011111001001110110000011000000110000000001100000011100001001100110001110001;
	assign dataIMAG[4] = 128'b11101110001111011011110111110111111001111100111111001100111110011011000001100110000001100000110010001000001000010010000111000100;
	assign dataIMAG[5] = 128'b10110110001111100111110011101111110110111001111111100110011100001111100011001100000000110001001000000100011000001100000111001001;
	assign dataIMAG[6] = 128'b10011100110111000011101100111011110001111110011111011001110110001111001000110010000011000000111000010001100100011110001001100011;
	assign dataIMAG[7] = 128'b10011000001111100111111111111101110011111110011100110011111111001110000000011001100011000000011000100000000000001100000111110011;
	assign dataIMAG[8] = 128'b11100111110000111101111111111110011111100111110011001111100100111001101100000110011000001100000011000000000000100001111000001100;
	assign dataIMAG[9] = 128'b11100011111000111100111011101110111110011011100111100111011001111000110010001100001100010011000011000100010001100001110000011100;
	assign dataIMAG[10] = 128'b11001001110001111111001110111011111111000111111011111001100011111000011100110000010000001110000010010001000110000000111000110110;
	assign dataIMAG[11] = 128'b10010011111001111110011111111100111111000111101100110011100011101100011100011001100100001110000001100000000011000000110000011011;
	assign dataIMAG[12] = 128'b11001111100110011111100111110011111101111101111011011110001110111001000111000010010000100000100010011000001100000011001100000110;
	assign dataIMAG[13] = 128'b10000111001100111111110011101101111110111001111100111110001101101100100111000001100000110001000000100100011000000001100110001111;
	assign dataIMAG[14] = 128'b10001101110011011111001111110001111011100110111000011101100111001110001100100011110001001100010000111000000110000010011000100111;
	assign dataIMAG[15] = 128'b10011111111001100111001111111001110111111111111100111110000011001110011111000001100000000000001000110000000110001100110000000011;
	assign dataIMAG[16] = 128'b11100000000110011000110000000110001000000000000011000001111100111001100000111110011111111111110111001111111001110011001111111100;
	assign dataIMAG[17] = 128'b11110010001100100000110000001110000100011001000111100010011000111001110011011100001110110011101111000111111001111101100111011000;
	assign dataIMAG[18] = 128'b11111000110011000000001100010010000001000110000011000001110010011011011000111110011111001110111111011011100111111110011001110000;
	assign dataIMAG[19] = 128'b10110000011001100000011000001100100010000010000100100001110001001110111000111101101111011111011111100111110011111100110011111001;
	assign dataIMAG[20] = 128'b11101100000110000001100000000011000000111000010011001100011100011011100011100110011011110001111110011111111100111111001111100100;
	assign dataIMAG[21] = 128'b10110110001110000000110001000100100000111000000100000110011100001111100011001111101111110001111111101110111001111111000111001001;
	assign dataIMAG[22] = 128'b10011100000111000011000100010001100001100100011000011000100110001111001101110011110011101100111110111011101110011110001111100011;
	assign dataIMAG[23] = 128'b10011000001111000010000000000001100000011000001100110000011011001110010011111001100111110011111100111111111111011110000111110011;
	assign dataIMAG[24] = 128'b11100111110000011000000000000010001100000001100011001100000000111001111111100110011100111111100111011111111111110011111000001100;
	assign dataIMAG[25] = 128'b11100011001000111100010011000100001110000001100000100110001001111000110111001101111100111111000111101110011011100001110110011100;
	assign dataIMAG[26] = 128'b11001001110000011000001100010000001001000110000000011001100011111000011100110011111111001110110111111011100111110011111000110110;
	assign dataIMAG[27] = 128'b10010001110000100100001000001000100110000011000000110011000001101100111110011001111110011111001111110111110111101101111000111011;
	assign dataIMAG[28] = 128'b11000111000110011001000011100000011000000000110000001100000110111001001111100111111001111111110011111100011110110011001110001110;
	assign dataIMAG[29] = 128'b10000111001100000100000011100000100100010001100000001110001101101100100111000111111100111011101111111100011111101111100110001111;
	assign dataIMAG[30] = 128'b10001100100011000011000100110000110001000100011000011100000111001110001111100011110011101110111011111001101110011110011101100111;
	assign dataIMAG[31] = 128'b10011011000001100110000011000000110000000000001000011110000011001110011111000011110111111111111001111110011111001100111110010011;


endmodule

src/sampleClockGen.v
`default_nettype none
`timescale 1ns/1ps
module sampleClockGen #(parameter CLK_DIV = 2,  CLK_TOTAL=127)(
            input CLOCK, RESET,
            output [6:0] COUNT,
            output SAMP, SHIFT
            );

    reg sample, shift;
    reg [6:0] pulseCount;

    assign COUNT = pulseCount;
    assign SAMP  = sample;
    assign SHIFT = shift;


    always @(posedge CLOCK)
        begin
            if(RESET)
            begin
                pulseCount <= 0;
                sample     <=  0;
                shift      <=  0;
            end
            else
            begin
                if(pulseCount == CLK_TOTAL-1)
                begin
                    pulseCount <= 0;
                    sample     <=  1;
                    shift      <=  0;   //consider leaving shift 0 when new samples are taken
                end
                else
                begin
                    pulseCount <= pulseCount + 1'b1;
                    sample     <=  0;
                    shift      <=  1;
                end
            end
        end

endmodule

src/mbsFSK.v
`default_nettype none
`timescale 1ns/1ps
module mbsFSK (
    input clk,    // 16MHz clock
    input reset,     //reset
    output READY,
    output SHIFT,
    output [4:0] LFSR,
    output [6:0] COUNT,
    output GPIO2,    //OUT2
    output GPIO1     //OUT1
);

    reg reset_d, reset_sync;
    wire outReal, outImag, ready, shift;
    wire [4:0] dataOut;
    wire [6:0] count;

    assign READY = ready;
    assign SHIFT = shift;
    assign LFSR  = dataOut;
    assign COUNT = count;
    assign GPIO2 = outReal;
    assign GPIO1 = outImag;

    //synchronize external reset
    always @(posedge clk)
    begin
        reset_d      <= reset;
        reset_sync   <= reset_d;
    end

    //MODULE INSTANTIATION
    sampleClockGen #(.CLK_DIV(1),  .CLK_TOTAL(128)) sampClockBlock (
        .CLOCK(clk),
        .RESET(reset_sync),
        .COUNT(count),
        .SAMP(ready),
        .SHIFT(shift));

    SymbLUT symbolLUT (
        .CLOCK(clk),
        .RESET(reset_sync),
        .READY(ready),
        .SHIFT(shift),
        .ADDRESS(dataOut),
        .DOUTREAL(outReal),
        .DOUTIMAG(outImag));

    LFSRmod prnGen (
        .CLOCK(clk),
        .RESET(reset_sync),
        .ENABLE(ready),
        .OUTDATA(dataOut));

endmodule

mbsFSK.vcd
$date
	Wed Aug 31 23:13:31 2022
$end
$version
	Icarus Verilog
$end
$timescale
	1ps
$end
$scope module mbsFSK $end
$var wire 7 ! COUNT [6:0] $end
$var wire 1 " GPIO1 $end
$var wire 1 # GPIO2 $end
$var wire 5 $ LFSR [4:0] $end
$var wire 1 % READY $end
$var wire 1 & SHIFT $end
$var wire 1 ' clk $end
$var wire 1 ( reset $end
$var wire 1 ) shift $end
$var wire 1 * ready $end
$var wire 1 + outReal $end
$var wire 1 , outImag $end
$var wire 5 - dataOut [4:0] $end
$var wire 7 . count [6:0] $end
$var reg 1 / reset_d $end
$var reg 1 0 reset_sync $end
$scope module prnGen $end
$var wire 1 ' CLOCK $end
$var wire 1 0 RESET $end
$var wire 1 * ENABLE $end
$var reg 5 1 OUTDATA [4:0] $end
$var reg 19 2 out [18:0] $end
$var reg 1 3 value $end
$upscope $end
$scope module sampClockBlock $end
$var wire 1 ' CLOCK $end
$var wire 1 0 RESET $end
$var wire 1 ) SHIFT $end
$var wire 1 * SAMP $end
$var wire 7 4 COUNT [6:0] $end
$var reg 7 5 pulseCount [6:0] $end
$var reg 1 * sample $end
$var reg 1 ) shift $end
$upscope $end
$scope module symbolLUT $end
$var wire 5 6 ADDRESS [4:0] $end
$var wire 1 ' CLOCK $end
$var wire 1 * READY $end
$var wire 1 0 RESET $end
$var wire 1 ) SHIFT $end
$var reg 1 , DOUTIMAG $end
$var reg 1 + DOUTREAL $end
$var reg 5 7 dataADDR_d [4:0] $end
$var reg 5 8 dataADDR_q [4:0] $end
$var reg 128 9 databuffIMAG [127:0] $end
$var reg 128 : databuffREAL [127:0] $end
$upscope $end
$upscope $end
$enddefinitions $end
#0
$dumpvars
bx :
bx 9
bx 8
bx 7
bx 6
bx 5
bx 4
x3
bx 2
bx 1
x0
1/
bx .
bx -
x,
x+
0*
1)
1(
1'
1&
0%
bx $
x#
x"
bx !
$end
#5000
0'
#10000
10
bx0 9
bx0 :
1'
#15000
0'
#20000
0"
0,
0#
0+
b0 $
b0 -
b0 1
b0 6
03
0&
0)
b0 !
b0 .
b0 4
b0 5
b0 9
b0 :
b0 7
b0 8
b1 2
1'
#25000
0'
#30000
1'
#35000
0'
#40000
1'
#45000
0'
#50000
1'
#55000
0'
#60000
1'
#65000
0'
#70000
1'
#75000
0'
#80000
1'
#85000
0'
#90000
1'
#95000
0'
#100000
1'
#105000
0'
#110000
1'
#115000
0'
#120000
1'
#125000
0'
#130000
1'
#135000
0'
#140000
1'
#145000
0'
#150000
1'
#155000
0'
#160000
1'
#165000
0'
#170000
1'
#175000
0'
#180000
1'
#185000
0'
#190000
1'
#195000
0'
#200000
1'
#205000
0'
#210000
1'
#215000
0'
#220000
1'
#225000
0'
#230000
1'
#235000
0'
#240000
1'
#245000
0'
#250000
1'
#255000
0'
#260000
1'
#265000
0'
#270000
1'
#275000
0'
#280000
1'
#285000
0'
#290000
1'
#295000
0'
#300000
1'
#305000
0'
#310000
1'
#315000
0'
#320000
1'
#325000
0'
#330000
1'
#335000
0'
#340000
1'
#345000
0'
#350000
1'
#355000
0'
#360000
1'
#365000
0'
#370000
1'
#375000
0'
#380000
1'
#385000
0'
#390000
1'
#395000
0'
#400000
1'
#405000
0'
#410000
1'
#415000
0'
#420000
1'
#425000
0'
#430000
1'
#435000
0'
#440000
1'
#445000
0'
#450000
1'
#455000
0'
#460000
1'
#465000
0'
#470000
1'
#475000
0'
#480000
1'
#485000
0'
#490000
0(
1'
#495000
0'
#500000
0/
1'
#505000
0'
#510000
00
1'
#515000
0'
#520000
1&
1)
b1 !
b1 .
b1 4
b1 5
1'
#525000
0'
#530000
b10 !
b10 .
b10 4
b10 5
1'
#535000
0'
#540000
b11 !
b11 .
b11 4
b11 5
1'
#545000
0'
#550000
b100 !
b100 .
b100 4
b100 5
1'
#555000
0'
#560000
b101 !
b101 .
b101 4
b101 5
1'
#565000
0'
#570000
b110 !
b110 .
b110 4
b110 5
1'
#575000
0'
#580000
b111 !
b111 .
b111 4
b111 5
1'
#585000
0'
#590000
b1000 !
b1000 .
b1000 4
b1000 5
1'
#595000
0'
#600000
b1001 !
b1001 .
b1001 4
b1001 5
1'
#605000
0'
#610000
b1010 !
b1010 .
b1010 4
b1010 5
1'
#615000
0'
#620000
b1011 !
b1011 .
b1011 4
b1011 5
1'
#625000
0'
#630000
b1100 !
b1100 .
b1100 4
b1100 5
1'
#635000
0'
#640000
b1101 !
b1101 .
b1101 4
b1101 5
1'
#645000
0'
#650000
b1110 !
b1110 .
b1110 4
b1110 5
1'
#655000
0'
#660000
b1111 !
b1111 .
b1111 4
b1111 5
1'
#665000
0'
#670000
b10000 !
b10000 .
b10000 4
b10000 5
1'
#675000
0'
#680000
b10001 !
b10001 .
b10001 4
b10001 5
1'
#685000
0'
#690000
b10010 !
b10010 .
b10010 4
b10010 5
1'
#695000
0'
#700000
b10011 !
b10011 .
b10011 4
b10011 5
1'
#705000
0'
#710000
b10100 !
b10100 .
b10100 4
b10100 5
1'
#715000
0'
#720000
b10101 !
b10101 .
b10101 4
b10101 5
1'
#725000
0'
#730000
b10110 !
b10110 .
b10110 4
b10110 5
1'
#735000
0'
#740000
b10111 !
b10111 .
b10111 4
b10111 5
1'
#745000
0'
#750000
b11000 !
b11000 .
b11000 4
b11000 5
1'
#755000
0'
#760000
b11001 !
b11001 .
b11001 4
b11001 5
1'
#765000
0'
#770000
b11010 !
b11010 .
b11010 4
b11010 5
1'
#775000
0'
#780000
b11011 !
b11011 .
b11011 4
b11011 5
1'
#785000
0'
#790000
b11100 !
b11100 .
b11100 4
b11100 5
1'
#795000
0'
#800000
b11101 !
b11101 .
b11101 4
b11101 5
1'
#805000
0'
#810000
b11110 !
b11110 .
b11110 4
b11110 5
1'
#815000
0'
#820000
b11111 !
b11111 .
b11111 4
b11111 5
1'
#825000
0'
#830000
b100000 !
b100000 .
b100000 4
b100000 5
1'
#835000
0'
#840000
b100001 !
b100001 .
b100001 4
b100001 5
1'
#845000
0'
#850000
b100010 !
b100010 .
b100010 4
b100010 5
1'
#855000
0'
#860000
b100011 !
b100011 .
b100011 4
b100011 5
1'
#865000
0'
#870000
b100100 !
b100100 .
b100100 4
b100100 5
1'
#875000
0'
#880000
b100101 !
b100101 .
b100101 4
b100101 5
1'
#885000
0'
#890000
b100110 !
b100110 .
b100110 4
b100110 5
1'
#895000
0'
#900000
b100111 !
b100111 .
b100111 4
b100111 5
1'
#905000
0'
#910000
b101000 !
b101000 .
b101000 4
b101000 5
1'
#915000
0'
#920000
b101001 !
b101001 .
b101001 4
b101001 5
1'
#925000
0'
#930000
b101010 !
b101010 .
b101010 4
b101010 5
1'
#935000
0'
#940000
b101011 !
b101011 .
b101011 4
b101011 5
1'
#945000
0'
#950000
b101100 !
b101100 .
b101100 4
b101100 5
1'
#955000
0'
#960000
b101101 !
b101101 .
b101101 4
b101101 5
1'
#965000
0'
#970000
b101110 !
b101110 .
b101110 4
b101110 5
1'
#975000
0'
#980000
b101111 !
b101111 .
b101111 4
b101111 5
1'
#985000
0'
#990000
b110000 !
b110000 .
b110000 4
b110000 5
1'
#995000
0'
#1000000
b110001 !
b110001 .
b110001 4
b110001 5
1'
#1005000
0'
#1010000
b110010 !
b110010 .
b110010 4
b110010 5
1'
#1015000
0'
#1020000
b110011 !
b110011 .
b110011 4
b110011 5
1'
#1025000
0'
#1030000
b110100 !
b110100 .
b110100 4
b110100 5
1'
#1035000
0'
#1040000
b110101 !
b110101 .
b110101 4
b110101 5
1'
#1045000
0'
#1050000
b110110 !
b110110 .
b110110 4
b110110 5
1'
#1055000
0'
#1060000
b110111 !
b110111 .
b110111 4
b110111 5
1'
#1065000
0'
#1070000
b111000 !
b111000 .
b111000 4
b111000 5
1'
#1075000
0'
#1080000
b111001 !
b111001 .
b111001 4
b111001 5
1'
#1085000
0'
#1090000
b111010 !
b111010 .
b111010 4
b111010 5
1'
#1095000
0'
#1100000
b111011 !
b111011 .
b111011 4
b111011 5
1'
#1105000
0'
#1110000
b111100 !
b111100 .
b111100 4
b111100 5
1'
#1115000
0'
#1120000
b111101 !
b111101 .
b111101 4
b111101 5
1'
#1125000
0'
#1130000
b111110 !
b111110 .
b111110 4
b111110 5
1'
#1135000
0'
#1140000
b111111 !
b111111 .
b111111 4
b111111 5
1'
#1145000
0'
#1150000
b1000000 !
b1000000 .
b1000000 4
b1000000 5
1'
#1155000
0'
#1160000
b1000001 !
b1000001 .
b1000001 4
b1000001 5
1'
#1165000
0'
#1170000
b1000010 !
b1000010 .
b1000010 4
b1000010 5
1'
#1175000
0'
#1180000
b1000011 !
b1000011 .
b1000011 4
b1000011 5
1'
#1185000
0'
#1190000
b1000100 !
b1000100 .
b1000100 4
b1000100 5
1'
#1195000
0'
#1200000
b1000101 !
b1000101 .
b1000101 4
b1000101 5
1'
#1205000
0'
#1210000
b1000110 !
b1000110 .
b1000110 4
b1000110 5
1'
#1215000
0'
#1220000
b1000111 !
b1000111 .
b1000111 4
b1000111 5
1'
#1225000
0'
#1230000
b1001000 !
b1001000 .
b1001000 4
b1001000 5
1'
#1235000
0'
#1240000
b1001001 !
b1001001 .
b1001001 4
b1001001 5
1'
#1245000
0'
#1250000
b1001010 !
b1001010 .
b1001010 4
b1001010 5
1'
#1255000
0'
#1260000
b1001011 !
b1001011 .
b1001011 4
b1001011 5
1'
#1265000
0'
#1270000
b1001100 !
b1001100 .
b1001100 4
b1001100 5
1'
#1275000
0'
#1280000
b1001101 !
b1001101 .
b1001101 4
b1001101 5
1'
#1285000
0'
#1290000
b1001110 !
b1001110 .
b1001110 4
b1001110 5
1'
#1295000
0'
#1300000
b1001111 !
b1001111 .
b1001111 4
b1001111 5
1'
#1305000
0'
#1310000
b1010000 !
b1010000 .
b1010000 4
b1010000 5
1'
#1315000
0'
#1320000
b1010001 !
b1010001 .
b1010001 4
b1010001 5
1'
#1325000
0'
#1330000
b1010010 !
b1010010 .
b1010010 4
b1010010 5
1'
#1335000
0'
#1340000
b1010011 !
b1010011 .
b1010011 4
b1010011 5
1'
#1345000
0'
#1350000
b1010100 !
b1010100 .
b1010100 4
b1010100 5
1'
#1355000
0'
#1360000
b1010101 !
b1010101 .
b1010101 4
b1010101 5
1'
#1365000
0'
#1370000
b1010110 !
b1010110 .
b1010110 4
b1010110 5
1'
#1375000
0'
#1380000
b1010111 !
b1010111 .
b1010111 4
b1010111 5
1'
#1385000
0'
#1390000
b1011000 !
b1011000 .
b1011000 4
b1011000 5
1'
#1395000
0'
#1400000
b1011001 !
b1011001 .
b1011001 4
b1011001 5
1'
#1405000
0'
#1410000
b1011010 !
b1011010 .
b1011010 4
b1011010 5
1'
#1415000
0'
#1420000
b1011011 !
b1011011 .
b1011011 4
b1011011 5
1'
#1425000
0'
#1430000
b1011100 !
b1011100 .
b1011100 4
b1011100 5
1'
#1435000
0'
#1440000
b1011101 !
b1011101 .
b1011101 4
b1011101 5
1'
#1445000
0'
#1450000
b1011110 !
b1011110 .
b1011110 4
b1011110 5
1'
#1455000
0'
#1460000
b1011111 !
b1011111 .
b1011111 4
b1011111 5
1'
#1465000
0'
#1470000
b1100000 !
b1100000 .
b1100000 4
b1100000 5
1'
#1475000
0'
#1480000
b1100001 !
b1100001 .
b1100001 4
b1100001 5
1'
#1485000
0'
#1490000
b1100010 !
b1100010 .
b1100010 4
b1100010 5
1'
#1495000
0'
#1500000
b1100011 !
b1100011 .
b1100011 4
b1100011 5
1'
#1505000
0'
#1510000
b1100100 !
b1100100 .
b1100100 4
b1100100 5
1'
#1515000
0'
#1520000
b1100101 !
b1100101 .
b1100101 4
b1100101 5
1'
#1525000
0'
#1530000
b1100110 !
b1100110 .
b1100110 4
b1100110 5
1'
#1535000
0'
#1540000
b1100111 !
b1100111 .
b1100111 4
b1100111 5
1'
#1545000
0'
#1550000
b1101000 !
b1101000 .
b1101000 4
b1101000 5
1'
#1555000
0'
#1560000
b1101001 !
b1101001 .
b1101001 4
b1101001 5
1'
#1565000
0'
#1570000
b1101010 !
b1101010 .
b1101010 4
b1101010 5
1'
#1575000
0'
#1580000
b1101011 !
b1101011 .
b1101011 4
b1101011 5
1'
#1585000
0'
#1590000
b1101100 !
b1101100 .
b1101100 4
b1101100 5
1'
#1595000
0'
#1600000
b1101101 !
b1101101 .
b1101101 4
b1101101 5
1'
#1605000
0'
#1610000
b1101110 !
b1101110 .
b1101110 4
b1101110 5
1'
#1615000
0'
#1620000
b1101111 !
b1101111 .
b1101111 4
b1101111 5
1'
#1625000
0'
#1630000
b1110000 !
b1110000 .
b1110000 4
b1110000 5
1'
#1635000
0'
#1640000
b1110001 !
b1110001 .
b1110001 4
b1110001 5
1'
#1645000
0'
#1650000
b1110010 !
b1110010 .
b1110010 4
b1110010 5
1'
#1655000
0'
#1660000
b1110011 !
b1110011 .
b1110011 4
b1110011 5
1'
#1665000
0'
#1670000
b1110100 !
b1110100 .
b1110100 4
b1110100 5
1'
#1675000
0'
#1680000
b1110101 !
b1110101 .
b1110101 4
b1110101 5
1'
#1685000
0'
#1690000
b1110110 !
b1110110 .
b1110110 4
b1110110 5
1'
#1695000
0'
#1700000
b1110111 !
b1110111 .
b1110111 4
b1110111 5
1'
#1705000
0'
#1710000
b1111000 !
b1111000 .
b1111000 4
b1111000 5
1'
#1715000
0'
#1720000
b1111001 !
b1111001 .
b1111001 4
b1111001 5
1'
#1725000
0'
#1730000
b1111010 !
b1111010 .
b1111010 4
b1111010 5
1'
#1735000
0'
#1740000
b1111011 !
b1111011 .
b1111011 4
b1111011 5
1'
#1745000
0'
#1750000
b1111100 !
b1111100 .
b1111100 4
b1111100 5
1'
#1755000
0'
#1760000
b1111101 !
b1111101 .
b1111101 4
b1111101 5
1'
#1765000
0'
#1770000
b1111110 !
b1111110 .
b1111110 4
b1111110 5
1'
#1775000
0'
#1780000
b1111111 !
b1111111 .
b1111111 4
b1111111 5
1'
#1785000
0'
#1790000
0&
0)
1%
1*
b0 !
b0 .
b0 4
b0 5
1'
#1795000
0'
#1800000
1"
1,
13
1&
1)
0%
0*
b1 !
b1 .
b1 4
b1 5
b11100100111110011001111100111111001111111111110111100001111100111001100000111100001000000000000110000001100000110011000001101100 9
b110000000011001100001110000011100110111111111001111100111111011101111110011111001111111110110011100000111000011001100000000110 :
b0 2
1'
#1805000
0'
#1810000
b11001001111100110011111001111110011111111111101111000011111001110011000001111000010000000000001100000011000001100110000011011000 9
b1100000000110011000011100000111001101111111110011111001111110111011111100111110011111111101100111000001110000110011000000001100 :
b10 !
b10 .
b10 4
b10 5
1'
#1815000
0'
#1820000
1#
1+
b11 !
b11 .
b11 4
b11 5
b10010011111001100111110011111100111111111111011110000111110011100110000011110000100000000000011000000110000011001100000110110000 9
b11000000001100110000111000001110011011111111100111110011111101110111111001111100111111111011001110000011100001100110000000011000 :
1'
#1825000
0'
#1830000
0"
0,
b100111110011001111100111111001111111111110111100001111100111001100000111100001000000000000110000001100000110011000001101100000 9
b10000000011001100001110000011100110111111111001111100111111011101111110011111001111111110110011100000111000011001100000000110000 :
b100 !
b100 .
b100 4
b100 5
1'
#1835000
0'
#1840000
0#
0+
b101 !
b101 .
b101 4
b101 5
b1001111100110011111001111110011111111111101111000011111001110011000001111000010000000000001100000011000001100110000011011000000 9
b110011000011100000111001101111111110011111001111110111011111100111110011111111101100111000001110000110011000000001100000 :
1'
#1845000
0'
#1850000
1"
1,
b10011111001100111110011111100111111111111011110000111110011100110000011110000100000000000011000000110000011001100000110110000000 9
b1100110000111000001110011011111111100111110011111101110111111001111100111111111011001110000011100001100110000000011000000 :
b110 !
b110 .
b110 4
b110 5
1'
#1855000
0'
#1860000
0"
0,
b111 !
b111 .
b111 4
b111 5
b111110011001111100111111001111111111110111100001111100111001100000111100001000000000000110000001100000110011000001101100000000 9
b11001100001110000011100110111111111001111100111111011101111110011111001111111110110011100000111000011001100000000110000000 :
1'
#1865000
0'
#1870000
b1111100110011111001111110011111111111101111000011111001110011000001111000010000000000001100000011000001100110000011011000000000 9
b110011000011100000111001101111111110011111001111110111011111100111110011111111101100111000001110000110011000000001100000000 :
b1000 !
b1000 .
b1000 4
b1000 5
1'
#1875000
0'
#1880000
1"
1,
b1001 !
b1001 .
b1001 4
b1001 5
b11111001100111110011111100111111111111011110000111110011100110000011110000100000000000011000000110000011001100000110110000000000 9
b1100110000111000001110011011111111100111110011111101110111111001111100111111111011001110000011100001100110000000011000000000 :
1'
#1885000
0'
#1890000
b11110011001111100111111001111111111110111100001111100111001100000111100001000000000000110000001100000110011000001101100000000000 9
b11001100001110000011100110111111111001111100111111011101111110011111001111111110110011100000111000011001100000000110000000000 :
b1010 !
b1010 .
b1010 4
b1010 5
1'
#1895000
0'
#1900000
b1011 !
b1011 .
b1011 4
b1011 5
b11100110011111001111110011111111111101111000011111001110011000001111000010000000000001100000011000001100110000011011000000000000 9
b110011000011100000111001101111111110011111001111110111011111100111110011111111101100111000001110000110011000000001100000000000 :
1'
