src/sampleClockGen.v
`default_nettype none
`timescale 1ns/1ps
module sampleClockGen #(parameter CLK_DIV = 2,  CLK_TOTAL=127)(
            input CLOCK, RESET,
            output [6:0] COUNT,
            output SAMP, SHIFT
            );

    reg sample, shift;
    reg [6:0] pulseCount;

    assign COUNT = pulseCount;
    assign SAMP  = sample;
    assign SHIFT = shift;


    always @(posedge CLOCK)
        begin
            if(RESET)
            begin
                pulseCount <= 0;
                sample     <=  0;
                shift      <=  0;
            end
            else
            begin
                if(pulseCount == CLK_TOTAL-1)
                begin
                    pulseCount <= 0;
                    sample     <=  1;
                    shift      <=  0;   //consider leaving shift 0 when new samples are taken
                end
                else
                begin
                    pulseCount <= pulseCount + 1'b1;
                    sample     <=  0;
                    shift      <=  1;
                end
            end
        end

endmodule

sampleClockGen.vcd
$date
	Wed Aug 31 23:13:40 2022
$end
$version
	Icarus Verilog
$end
$timescale
	1ps
$end
$scope module sampleClockGen $end
$var wire 1 ! CLOCK $end
$var wire 7 " COUNT [6:0] $end
$var wire 1 # RESET $end
$var wire 1 $ SAMP $end
$var wire 1 % SHIFT $end
$var reg 7 & pulseCount [6:0] $end
$var reg 1 ' sample $end
$var reg 1 ( shift $end
$upscope $end
$enddefinitions $end
#0
$dumpvars
0(
0'
b0 &
0%
0$
1#
b0 "
1!
$end
#5000
0!
#10000
1!
#15000
0!
#20000
1!
#25000
0!
#30000
1!
#35000
0!
#40000
1!
#45000
0!
#50000
1!
#55000
0!
#60000
1!
#65000
0!
#70000
1!
#75000
0!
#80000
1!
#85000
0!
#90000
1!
#95000
0!
#100000
1!
#105000
0!
#110000
1!
#115000
0!
#120000
1!
#125000
0!
#130000
1!
#135000
0!
#140000
1!
#145000
0!
#150000
1!
#155000
0!
#160000
1!
#165000
0!
#170000
1!
#175000
0!
#180000
1!
#185000
0!
#190000
1!
#195000
0!
#200000
1!
#205000
0!
#210000
1!
#215000
0!
#220000
1!
#225000
0!
#230000
1!
#235000
0!
#240000
1!
#245000
0!
#250000
1!
#255000
0!
#260000
1!
#265000
0!
#270000
1!
#275000
0!
#280000
1!
#285000
0!
#290000
1!
#295000
0!
#300000
1!
#305000
0!
#310000
1!
#315000
0!
#320000
1!
#325000
0!
#330000
1!
#335000
0!
#340000
1!
#345000
0!
#350000
1!
#355000
0!
#360000
1!
#365000
0!
#370000
1!
#375000
0!
#380000
1!
#385000
0!
#390000
1!
#395000
0!
#400000
1!
#405000
0!
#410000
1!
#415000
0!
#420000
1!
#425000
0!
#430000
1!
#435000
0!
#440000
1!
#445000
0!
#450000
1!
#455000
0!
#460000
1!
#465000
0!
#470000
1!
#475000
0!
#480000
1!
#485000
0!
#490000
0#
1!
#495000
0!
#500000
1%
1(
b1 "
b1 &
1!
#505000
0!
#510000
b10 "
b10 &
1!
#515000
0!
#520000
b11 "
b11 &
1!
#525000
0!
#530000
b100 "
b100 &
1!
#535000
0!
#540000
b101 "
b101 &
1!
#545000
0!
#550000
b110 "
b110 &
1!
#555000
0!
#560000
b111 "
b111 &
1!
#565000
0!
#570000
b1000 "
b1000 &
1!
#575000
0!
#580000
b1001 "
b1001 &
1!
#585000
0!
#590000
b1010 "
b1010 &
1!
#595000
0!
#600000
b1011 "
b1011 &
1!
#605000
0!
#610000
b1100 "
b1100 &
1!
#615000
0!
#620000
b1101 "
b1101 &
1!
#625000
0!
#630000
b1110 "
b1110 &
1!
#635000
0!
#640000
b1111 "
b1111 &
1!
#645000
0!
#650000
b10000 "
b10000 &
1!
#655000
0!
#660000
b10001 "
b10001 &
1!
#665000
0!
#670000
b10010 "
b10010 &
1!
#675000
0!
#680000
b10011 "
b10011 &
1!
#685000
0!
#690000
b10100 "
b10100 &
1!
#695000
0!
#700000
b10101 "
b10101 &
1!
#705000
0!
#710000
b10110 "
b10110 &
1!
#715000
0!
#720000
b10111 "
b10111 &
1!
#725000
0!
#730000
b11000 "
b11000 &
1!
#735000
0!
#740000
b11001 "
b11001 &
1!
#745000
0!
#750000
b11010 "
b11010 &
1!
#755000
0!
#760000
b11011 "
b11011 &
1!
#765000
0!
#770000
b11100 "
b11100 &
1!
#775000
0!
#780000
b11101 "
b11101 &
1!
#785000
0!
#790000
b11110 "
b11110 &
1!
#795000
0!
#800000
b11111 "
b11111 &
1!
#805000
0!
#810000
b100000 "
b100000 &
1!
#815000
0!
#820000
b100001 "
b100001 &
1!
#825000
0!
#830000
b100010 "
b100010 &
1!
#835000
0!
#840000
b100011 "
b100011 &
1!
#845000
0!
#850000
b100100 "
b100100 &
1!
#855000
0!
#860000
b100101 "
b100101 &
1!
#865000
0!
#870000
b100110 "
b100110 &
1!
#875000
0!
#880000
b100111 "
b100111 &
1!
#885000
0!
#890000
b101000 "
b101000 &
1!
#895000
0!
#900000
b101001 "
b101001 &
1!
#905000
0!
#910000
b101010 "
b101010 &
1!
#915000
0!
#920000
b101011 "
b101011 &
1!
#925000
0!
#930000
b101100 "
b101100 &
1!
#935000
0!
#940000
b101101 "
b101101 &
1!
#945000
0!
#950000
b101110 "
b101110 &
1!
#955000
0!
#960000
b101111 "
b101111 &
1!
#965000
0!
#970000
b110000 "
b110000 &
1!
#975000
0!
#980000
b110001 "
b110001 &
1!
#985000
0!
#990000
b110010 "
b110010 &
1!
#995000
0!
#1000000
b110011 "
b110011 &
1!
#1005000
0!
#1010000
b110100 "
b110100 &
1!
#1015000
0!
#1020000
b110101 "
b110101 &
1!
#1025000
0!
#1030000
b110110 "
b110110 &
1!
#1035000
0!
#1040000
b110111 "
b110111 &
1!
#1045000
0!
#1050000
b111000 "
b111000 &
1!
#1055000
0!
#1060000
b111001 "
b111001 &
1!
#1065000
0!
#1070000
b111010 "
b111010 &
1!
#1075000
0!
#1080000
b111011 "
b111011 &
1!
#1085000
0!
#1090000
b111100 "
b111100 &
1!
#1095000
0!
#1100000
b111101 "
b111101 &
1!
#1105000
0!
#1110000
b111110 "
b111110 &
1!
#1115000
0!
#1120000
b111111 "
b111111 &
1!
#1125000
0!
#1130000
b1000000 "
b1000000 &
1!
#1135000
0!
#1140000
b1000001 "
b1000001 &
1!
#1145000
0!
#1150000
b1000010 "
b1000010 &
1!
#1155000
0!
#1160000
b1000011 "
b1000011 &
1!
#1165000
0!
#1170000
b1000100 "
b1000100 &
1!
#1175000
0!
#1180000
b1000101 "
b1000101 &
1!
#1185000
0!
#1190000
b1000110 "
b1000110 &
1!
#1195000
0!
#1200000
b1000111 "
b1000111 &
1!
#1205000
0!
#1210000
b1001000 "
b1001000 &
1!
#1215000
0!
#1220000
b1001001 "
b1001001 &
1!
#1225000
0!
#1230000
b1001010 "
b1001010 &
1!
#1235000
0!
#1240000
b1001011 "
b1001011 &
1!
#1245000
0!
#1250000
b1001100 "
b1001100 &
1!
#1255000
0!
#1260000
b1001101 "
b1001101 &
1!
#1265000
0!
#1270000
b1001110 "
b1001110 &
1!
#1275000
0!
#1280000
b1001111 "
b1001111 &
1!
#1285000
0!
#1290000
b1010000 "
b1010000 &
1!
#1295000
0!
#1300000
b1010001 "
b1010001 &
1!
#1305000
0!
#1310000
b1010010 "
b1010010 &
1!
#1315000
0!
#1320000
b1010011 "
b1010011 &
1!
#1325000
0!
#1330000
b1010100 "
b1010100 &
1!
#1335000
0!
#1340000
b1010101 "
b1010101 &
1!
#1345000
0!
#1350000
b1010110 "
b1010110 &
1!
#1355000
0!
#1360000
b1010111 "
b1010111 &
1!
#1365000
0!
#1370000
b1011000 "
b1011000 &
1!
#1375000
0!
#1380000
b1011001 "
b1011001 &
1!
#1385000
0!
#1390000
b1011010 "
b1011010 &
1!
#1395000
0!
#1400000
b1011011 "
b1011011 &
1!
#1405000
0!
#1410000
b1011100 "
b1011100 &
1!
#1415000
0!
#1420000
b1011101 "
b1011101 &
1!
#1425000
0!
#1430000
b1011110 "
b1011110 &
1!
#1435000
0!
#1440000
b1011111 "
b1011111 &
1!
#1445000
0!
#1450000
b1100000 "
b1100000 &
1!
#1455000
0!
#1460000
b1100001 "
b1100001 &
1!
#1465000
0!
#1470000
b1100010 "
b1100010 &
1!
#1475000
0!
#1480000
b1100011 "
b1100011 &
1!
#1485000
0!
#1490000
b1100100 "
b1100100 &
1!
#1495000
0!
#1500000
b1100101 "
b1100101 &
1!
#1505000
0!
#1510000
b1100110 "
b1100110 &
1!
#1515000
0!
#1520000
b1100111 "
b1100111 &
1!
#1525000
0!
#1530000
b1101000 "
b1101000 &
1!
#1535000
0!
#1540000
b1101001 "
b1101001 &
1!
#1545000
0!
#1550000
b1101010 "
b1101010 &
1!
#1555000
0!
#1560000
b1101011 "
b1101011 &
1!
#1565000
0!
#1570000
b1101100 "
b1101100 &
1!
#1575000
0!
#1580000
b1101101 "
b1101101 &
1!
#1585000
0!
#1590000
b1101110 "
b1101110 &
1!
#1595000
0!
#1600000
b1101111 "
b1101111 &
1!
#1605000
0!
#1610000
b1110000 "
b1110000 &
1!
#1615000
0!
#1620000
b1110001 "
b1110001 &
1!
#1625000
0!
#1630000
b1110010 "
b1110010 &
1!
#1635000
0!
#1640000
b1110011 "
b1110011 &
1!
#1645000
0!
#1650000
b1110100 "
b1110100 &
1!
#1655000
0!
#1660000
b1110101 "
b1110101 &
1!
#1665000
0!
#1670000
b1110110 "
b1110110 &
1!
#1675000
0!
#1680000
b1110111 "
b1110111 &
1!
#1685000
0!
#1690000
b1111000 "
b1111000 &
1!
#1695000
0!
#1700000
b1111001 "
b1111001 &
1!
#1705000
0!
#1710000
b1111010 "
b1111010 &
1!
#1715000
0!
#1720000
b1111011 "
b1111011 &
1!
#1725000
0!
#1730000
b1111100 "
b1111100 &
1!
#1735000
0!
#1740000
b1111101 "
b1111101 &
1!
#1745000
0!
#1750000
b1111110 "
b1111110 &
1!
#1755000
0!
#1760000
0%
0(
1$
1'
b0 "
b0 &
1!
#1765000
0!
#1770000
1%
1(
0$
0'
b1 "
b1 &
1!
#1775000
0!
#1780000
b10 "
b10 &
1!
#1785000
0!
#1790000
b11 "
b11 &
1!
#1795000
0!
#1800000
b100 "
b100 &
1!
#1805000
0!
#1810000
b101 "
b101 &
1!
#1815000
0!
#1820000
b110 "
b110 &
1!
#1825000
0!
#1830000
b111 "
b111 &
1!
#1835000
0!
#1840000
b1000 "
b1000 &
1!
#1845000
0!
#1850000
b1001 "
b1001 &
1!
#1855000
0!
#1860000
b1010 "
b1010 &
1!
#1865000
0!
#1870000
b1011 "
b1011 &
1!
